rozper/__init__.py
rozper/core.py
rozper-0.1.0.dist-info/licenses/LICENSE
rozper-0.1.0.dist-info/METADATA
rozper-0.1.0.dist-info/WHEEL
rozper-0.1.0.dist-info/top_level.txt
rozper-0.1.0.dist-info/RECORD
